{
  "routes": [
    {
      "method": "GET",
      "path": "/climas",
      "handler": "clima.find",
      "config": {
        "policies": []
      }
    },
    {
      "method": "GET",
      "path": "/climas/count",
      "handler": "clima.count",
      "config": {
        "policies": []
      }
    },
    {
      "method": "GET",
      "path": "/climas/:id",
      "handler": "clima.findOne",
      "config": {
        "policies": []
      }
    },
    {
      "method": "POST",
      "path": "/climas",
      "handler": "clima.create",
      "config": {
        "policies": []
      }
    },
    {
      "method": "PUT",
      "path": "/climas/:id",
      "handler": "clima.update",
      "config": {
        "policies": []
      }
    },
    {
      "method": "DELETE",
      "path": "/climas/:id",
      "handler": "clima.delete",
      "config": {
        "policies": []
      }
    }
  ]
}
